cli_board_manager/__init__.py
cli_board_manager/app.py
cli_board_manager/app.tcss
cli_board_manager/py.typed
cli_board_manager-1.1.0.dist-info/WHEEL
cli_board_manager-1.1.0.dist-info/entry_points.txt
cli_board_manager-1.1.0.dist-info/METADATA
cli_board_manager-1.1.0.dist-info/RECORD
