Metadata-Version: 2.4
Name: cli-board-manager
Version: 1.1.0
Summary: A clipboard manager for the terminal written in Python with the ✨awesome✨ Textual framework.
Author: David Fokkema
Author-email: David Fokkema <davidfokkema@icloud.com>
License-Expression: GPL-3.0-or-later
Classifier: Development Status :: 5 - Production/Stable
Classifier: Environment :: Console
Classifier: Intended Audience :: End Users/Desktop
Classifier: License :: OSI Approved :: GNU General Public License v3 or later (GPLv3+)
Classifier: Operating System :: MacOS
Classifier: Operating System :: Microsoft :: Windows
Classifier: Operating System :: POSIX
Classifier: Programming Language :: Python
Requires-Dist: pyperclip>=1.11.0
Requires-Dist: textual>=6.3.0
Requires-Python: >=3.10
Project-URL: changelog, https://github.com/davidfokkema/cli-board-manager/blob/main/CHANGELOG.md
Project-URL: homepage, https://github.com/davidfokkema/cli-board-manager
Project-URL: issues, https://github.com/davidfokkema/cli-board-manager/issues
Project-URL: source, https://github.com/davidfokkema/cli-board-manager
